{
    "layout": "oxen-layout",
    "title": "Payment confirmed - Oxen",
    "greeting": "Hi",
    "payment_confirmed_message_prefix": "Your payment of",
    "payment_confirmed_message_middle": "at",
    "payment_confirmed_message_suffix": "was successful.",
    "cta_message": "👉 View transaction history in your app.",
    "security_warning": "If this wasn't you, please contact our support immediately.",
    "signature": "The Oxen Team.",
    "subject": "💸 Payment of {{amount}} to {{merchant}} confirmed",
    "amount": "€643.14",
    "first_name": "",
    "merchant": "Carrefour",
    "recipient_email": ""
}
